etherpump/__init__.py
etherpump/api/__init__.py
etherpump/commands/__init__.py
etherpump/commands/appendmeta.py
etherpump/commands/common.py
etherpump/commands/creatediffhtml.py
etherpump/commands/deletepad.py
etherpump/commands/dumpcsv.py
etherpump/commands/gethtml.py
etherpump/commands/gettext.py
etherpump/commands/html5tidy.py
etherpump/commands/index.py
etherpump/commands/init.py
etherpump/commands/join.py
etherpump/commands/list.py
etherpump/commands/listauthors.py
etherpump/commands/publication.py
etherpump/commands/pull.py
etherpump/commands/revisionscount.py
etherpump/commands/sethtml.py
etherpump/commands/settext.py
etherpump/commands/showmeta.py
etherpump/commands/status.py
etherpump/data/templates/index.html
etherpump/data/templates/pad.html
etherpump/data/templates/pad_colors.html
etherpump/data/templates/pad_index.html
etherpump/data/templates/publication.html
etherpump/data/templates/rss.xml
etherpump-0.0.19.dist-info/entry_points.txt
etherpump-0.0.19.dist-info/LICENSE
etherpump-0.0.19.dist-info/WHEEL
etherpump-0.0.19.dist-info/METADATA
etherpump-0.0.19.dist-info/RECORD
