Metadata-Version: 2.1
Name: etherpump
Version: 0.0.19
Summary: Pumping text from etherpads into publications
Home-page: https://git.vvvvvvaria.org/varia/etherpump
License: GPLv3
Keywords: etherpad,etherdump,etherpump
Author: Varia, Center for Everyday Technology
Maintainer: Varia, Center for Everyday Technology
Maintainer-email: info@varia.zone
Requires-Python: >=3.6,<4.0
Classifier: License :: Other/Proprietary License
Classifier: Programming Language :: Python :: 3
Classifier: Programming Language :: Python :: 3.6
Classifier: Programming Language :: Python :: 3.7
Classifier: Programming Language :: Python :: 3.8
Classifier: Programming Language :: Python :: 3.9
Requires-Dist: asks (>=2.4.10,<3.0.0)
Requires-Dist: html5lib (>=1.1,<2.0)
Requires-Dist: jinja2 (>=2.11.2,<3.0.0)
Requires-Dist: pypandoc (>=1.5,<2.0)
Requires-Dist: python-dateutil (>=2.8.1,<3.0.0)
Requires-Dist: requests (>=2.24.0,<3.0.0)
Requires-Dist: trio (>=0.17.0,<0.18.0)
Project-URL: Repository, https://git.vvvvvvaria.org/varia/etherpump
